{
  "waypoints": [
    {
      "lat": 34.0522,
      "lon": -118.2437,
      "alt_m": 16500.0,
      "time_utc": "2026-02-09T18:00:00Z"
    },
    {
      "lat": 35.4676,
      "lon": -111.6513,
      "alt_m": 16500.0,
      "time_utc": "2026-02-09T18:30:00Z"
    },
    {
      "lat": 35.1983,
      "lon": -101.8313,
      "alt_m": 16500.0,
      "time_utc": "2026-02-09T19:10:00Z"
    },
    {
      "lat": 32.7767,
      "lon": -96.7970,
      "alt_m": 16500.0,
      "time_utc": "2026-02-09T19:40:00Z"
    }
  ]
}
